subplz/__init__.py
subplz/cli.py
subplz/config.py
subplz/main.py
subplz/pipeline.py
subplz/tui.py
subplz/tui_demo.py
subtitle_for_everyone-1.1.2.dist-info/licenses/LICENSE
subtitle_for_everyone-1.1.2.dist-info/METADATA
subtitle_for_everyone-1.1.2.dist-info/WHEEL
subtitle_for_everyone-1.1.2.dist-info/entry_points.txt
subtitle_for_everyone-1.1.2.dist-info/top_level.txt
subtitle_for_everyone-1.1.2.dist-info/RECORD
