Metadata-Version: 2.4
Name: subtitle-for-everyone
Version: 1.1.2
Summary: Professional subtitle generation - made for anime enthusiast
Author-email: Sid & Kan <sofiyasenthilkumar@gmail.com>
Project-URL: Homepage, https://github.com/guider23/subplz
Project-URL: Bug Reports, https://github.com/guider23/subplz/issues
Project-URL: Source, https://github.com/guider23/subplz
Keywords: youtube,subtitles,video,tui,terminal,interface,whisper,ffmpeg,textual
Classifier: Development Status :: 4 - Beta
Classifier: Intended Audience :: End Users/Desktop
Classifier: License :: OSI Approved :: MIT License
Classifier: Operating System :: OS Independent
Classifier: Programming Language :: Python :: 3
Classifier: Programming Language :: Python :: 3.8
Classifier: Programming Language :: Python :: 3.9
Classifier: Programming Language :: Python :: 3.10
Classifier: Programming Language :: Python :: 3.11
Classifier: Programming Language :: Python :: 3.12
Classifier: Topic :: Multimedia :: Video
Classifier: Topic :: Software Development :: Libraries :: Python Modules
Requires-Python: >=3.8
License-File: LICENSE
Requires-Dist: yt-dlp>=2023.7.6
Requires-Dist: openai-whisper==20231117
Requires-Dist: torch==2.0.1
Requires-Dist: ffmpeg-python>=0.2.0
Requires-Dist: tqdm>=4.65.0
Requires-Dist: textual>=0.41.0
Requires-Dist: rich>=13.0.0
Provides-Extra: dev
Requires-Dist: pytest>=7.0; extra == "dev"
Requires-Dist: black>=22.0; extra == "dev"
Requires-Dist: isort>=5.0; extra == "dev"
Requires-Dist: flake8>=4.0; extra == "dev"
Dynamic: license-file
